geneticocolor/__init__.py
geneticocolor/color_generator.py
geneticocolor/oRGB.py
geneticocolor-0.0.9.dist-info/METADATA
geneticocolor-0.0.9.dist-info/RECORD
geneticocolor-0.0.9.dist-info/WHEEL
geneticocolor-0.0.9.dist-info/top_level.txt
